ifc_anywidget/__init__.py
ifc_anywidget/index.css
ifc_anywidget/index.js
ifc_anywidget-0.3.0.dist-info/METADATA
ifc_anywidget-0.3.0.dist-info/WHEEL
ifc_anywidget-0.3.0.dist-info/licenses/LICENSE
ifc_anywidget-0.3.0.dist-info/RECORD
