Metadata-Version: 2.4
Name: ifc-anywidget
Version: 0.3.0
Summary: IFC viewer AnyWidget using That Open Company Open BIM Components
Project-URL: Source, https://github.com/sanzoghenzo/ifc-anywidget
Author: sanzoghenzo
License: Copyright (c) 2025 Andrea Ghensi
License-File: LICENSE
Requires-Python: >=3.10
Requires-Dist: anywidget>=0.9.18
Requires-Dist: ifcopenshell>=0.8.2
